[
  {
    "text": "moin",
    "intent": "greet",
    "intent_prediction": {
      "name": "mood_great",
      "confidence": 0.30965858697891235
    }
  },
  {
    "text": "have a nice day",
    "intent": "goodbye",
    "intent_prediction": {
      "name": "mood_unhappy",
      "confidence": 0.47842732071876526
    }
  },
  {
    "text": "yes",
    "intent": "affirm",
    "intent_prediction": {
      "name": "goodbye",
      "confidence": 0.9055413603782654
    }
  },
  {
    "text": "y",
    "intent": "affirm",
    "intent_prediction": {
      "name": "deny",
      "confidence": 0.6840624809265137
    }
  },
  {
    "text": "my day was horrible",
    "intent": "mood_unhappy",
    "intent_prediction": {
      "name": "deny",
      "confidence": 0.7480418086051941
    }
  },
  {
    "text": "I am disappointed",
    "intent": "mood_unhappy",
    "intent_prediction": {
      "name": "mood_great",
      "confidence": 0.834629237651825
    }
  },
  {
    "text": "indeed",
    "intent": "affirm",
    "intent_prediction": {
      "name": "mood_great",
      "confidence": 0.6608351469039917
    }
  },
  {
    "text": "not really",
    "intent": "deny",
    "intent_prediction": {
      "name": "mood_unhappy",
      "confidence": 0.9991130232810974
    }
  },
  {
    "text": "về đây",
    "intent": "goodbye",
    "intent_prediction": {
      "name": "affirm",
      "confidence": 0.41710594296455383
    }
  },
  {
    "text": "correct",
    "intent": "affirm",
    "intent_prediction": {
      "name": "mood_great",
      "confidence": 0.9929814338684082
    }
  },
  {
    "text": "extremely good",
    "intent": "mood_great",
    "intent_prediction": {
      "name": "mood_unhappy",
      "confidence": 0.9997013211250305
    }
  },
  {
    "text": "so good",
    "intent": "mood_great",
    "intent_prediction": {
      "name": "mood_unhappy",
      "confidence": 0.9360249638557434
    }
  },
  {
    "text": "that sounds good",
    "intent": "affirm",
    "intent_prediction": {
      "name": "mood_great",
      "confidence": 0.741448163986206
    }
  },
  {
    "text": "I don't think so",
    "intent": "deny",
    "intent_prediction": {
      "name": "mood_unhappy",
      "confidence": 0.4972855746746063
    }
  },
  {
    "text": "not good",
    "intent": "mood_unhappy",
    "intent_prediction": {
      "name": "deny",
      "confidence": 0.9634303450584412
    }
  },
  {
    "text": "not very good",
    "intent": "mood_unhappy",
    "intent_prediction": {
      "name": "deny",
      "confidence": 0.8862592577934265
    }
  },
  {
    "text": "let's go",
    "intent": "greet",
    "intent_prediction": {
      "name": "mood_great",
      "confidence": 0.7854737043380737
    }
  },
  {
    "text": "good afternoon",
    "intent": "greet",
    "intent_prediction": {
      "name": "mood_great",
      "confidence": 0.7999177575111389
    }
  },
  {
    "text": "good night",
    "intent": "goodbye",
    "intent_prediction": {
      "name": "greet",
      "confidence": 0.4094436466693878
    }
  },
  {
    "text": "super stoked",
    "intent": "mood_great",
    "intent_prediction": {
      "name": "mood_unhappy",
      "confidence": 0.9984180927276611
    }
  },
  {
    "text": "I don't feel very well",
    "intent": "mood_unhappy",
    "intent_prediction": {
      "name": "deny",
      "confidence": 0.6556019186973572
    }
  },
  {
    "text": "unhappy",
    "intent": "mood_unhappy",
    "intent_prediction": {
      "name": "affirm",
      "confidence": 0.8198397755622864
    }
  }
]